secml/VERSION
secml/VERSION_REV
secml/__init__.py
secml/_globals.py
secml/secml.conf
secml/settings.py
secml/test_simple.py
secml/adv/__init__.py
secml/adv/attacks/__init__.py
secml/adv/attacks/c_attack.py
secml/adv/attacks/c_attack_mixin.py
secml/adv/attacks/evasion/__init__.py
secml/adv/attacks/evasion/c_attack_evasion.py
secml/adv/attacks/evasion/c_attack_evasion_pgd.py
secml/adv/attacks/evasion/c_attack_evasion_pgd_exp.py
secml/adv/attacks/evasion/c_attack_evasion_pgd_ls.py
secml/adv/attacks/evasion/cleverhans/__init__.py
secml/adv/attacks/evasion/cleverhans/c_attack_evasion_cleverhans.py
secml/adv/attacks/evasion/cleverhans/c_attack_evasion_cleverhans_losses.py
secml/adv/attacks/evasion/foolbox/__init__.py
secml/adv/attacks/evasion/foolbox/c_attack_evasion_foolbox.py
secml/adv/attacks/evasion/foolbox/secml_autograd.py
secml/adv/attacks/evasion/foolbox/fb_attacks/__init__.py
secml/adv/attacks/evasion/foolbox/fb_attacks/fb_basic_iterative_attack.py
secml/adv/attacks/evasion/foolbox/fb_attacks/fb_cw_attack.py
secml/adv/attacks/evasion/foolbox/fb_attacks/fb_ddn_attack.py
secml/adv/attacks/evasion/foolbox/fb_attacks/fb_deepfool_attack.py
secml/adv/attacks/evasion/foolbox/fb_attacks/fb_ead_attack.py
secml/adv/attacks/evasion/foolbox/fb_attacks/fb_fgm_attack.py
secml/adv/attacks/evasion/foolbox/fb_attacks/fb_pgd_attack.py
secml/adv/attacks/evasion/foolbox/losses/__init__.py
secml/adv/attacks/evasion/foolbox/losses/ce_loss.py
secml/adv/attacks/evasion/foolbox/losses/cw_loss.py
secml/adv/attacks/evasion/foolbox/losses/deepfool_loss.py
secml/adv/attacks/evasion/foolbox/losses/ead_loss.py
secml/adv/attacks/evasion/foolbox/losses/logits_loss.py
secml/adv/attacks/poisoning/__init__.py
secml/adv/attacks/poisoning/c_attack_poisoning.py
secml/adv/attacks/poisoning/c_attack_poisoning_logistic_regression.py
secml/adv/attacks/poisoning/c_attack_poisoning_ridge.py
secml/adv/attacks/poisoning/c_attack_poisoning_svm.py
secml/adv/seceval/__init__.py
secml/adv/seceval/c_sec_eval.py
secml-0.15.6.dist-info/LICENSE
secml-0.15.6.dist-info/METADATA
secml-0.15.6.dist-info/WHEEL
secml-0.15.6.dist-info/top_level.txt
secml-0.15.6.dist-info/RECORD
