Metadata-Version: 2.1
Name: secml
Version: 0.15.6
Summary: A library for Secure and Explainable Machine Learning
Home-page: https://secml.readthedocs.io
Download-URL: https://pypi.python.org/pypi/secml#files
Maintainer: Maura Pintor, Luca Demetrio
Maintainer-email: maura.pintor@unica.it, luca.demetrio@unige.it
License: Apache License 2.0
Project-URL: Bug Tracker, https://github.com/pralab/secml/issues
Project-URL: Source Code, https://github.com/pralab/secml
Platform: Linux
Platform: Mac OS-X
Platform: Unix
Platform: Windows
Classifier: Development Status :: 3 - Alpha
Classifier: Intended Audience :: Science/Research
Classifier: Intended Audience :: Developers
Classifier: License :: OSI Approved
Classifier: Programming Language :: Python
Classifier: Programming Language :: Python :: 3
Classifier: Programming Language :: Python :: 3.6
Classifier: Programming Language :: Python :: 3.7
Classifier: Programming Language :: Python :: 3.8
Classifier: Programming Language :: Python :: 3.9
Classifier: Programming Language :: Python :: 3.10
Classifier: Programming Language :: Python :: Implementation :: PyPy
Classifier: Topic :: Software Development
Classifier: Topic :: Scientific/Engineering
Classifier: Operating System :: POSIX
Classifier: Operating System :: Unix
Classifier: Operating System :: MacOS
Classifier: Operating System :: Microsoft :: Windows
Requires-Python: >=3.5, <3.11
Provides-Extra: pytorch
Provides-Extra: cleverhans
Provides-Extra: tf-gpu
Provides-Extra: foolbox
Provides-Extra: unittests
License-File: LICENSE
